{
    "Rounding1_PP": {
        "AllCompiledSampleTimes": [
            [
                0.1,
                0
            ]
        ],
        "BlockType": "block_diagram",
        "CompiledSampleTime": [
            0.1,
            0
        ],
        "Content": {
            "In1": {
                "AttributesFormatString": "",
                "BlockType": "Inport",
                "BusObject": "BusObject",
                "CompiledPortComplexSignals": {
                    "Enable": [],
                    "Ifaction": [],
                    "Inport": [],
                    "LConn": [],
                    "Outport": 0,
                    "RConn": [],
                    "Reset": [],
                    "State": [],
                    "Trigger": []
                },
                "CompiledPortDataTypes": {
                    "Enable": [],
                    "Ifaction": [],
                    "Inport": [],
                    "LConn": [],
                    "Outport": [
                        "double"
                    ],
                    "RConn": [],
                    "Reset": [],
                    "State": [],
                    "Trigger": []
                },
                "CompiledPortDimensions": {
                    "Enable": [],
                    "Ifaction": [],
                    "Inport": [],
                    "LConn": [],
                    "Outport": [
                        1,
                        1
                    ],
                    "RConn": [],
                    "Reset": [],
                    "State": [],
                    "Trigger": []
                },
                "CompiledPortWidths": {
                    "Enable": [],
                    "Ifaction": [],
                    "Inport": [],
                    "LConn": [],
                    "Outport": 1,
                    "RConn": [],
                    "Reset": [],
                    "State": [],
                    "Trigger": []
                },
                "CompiledSampleTime": [
                    0.1,
                    0
                ],
                "Handle": 118.9732666015625,
                "LineHandles": {
                    "Enable": [],
                    "Ifaction": [],
                    "Inport": [],
                    "LConn": [],
                    "Outport": 311.3594970703125,
                    "RConn": [],
                    "Reset": [],
                    "State": [],
                    "Trigger": []
                },
                "Name": "In1",
                "Origin_path": "Rounding1_PP/In1",
                "OutMax": "[]",
                "OutMin": "[]",
                "Path": "Rounding1_PP/In1",
                "Port": "1",
                "PortConnectivity": {
                    "DstBlock": 165.8046875,
                    "DstPort": 0,
                    "Position": [
                        325,
                        330
                    ],
                    "SrcBlock": [],
                    "SrcPort": [],
                    "Type": "1"
                },
                "Ports": [
                    0,
                    1,
                    0,
                    0,
                    0,
                    0,
                    0,
                    0,
                    0
                ],
                "Position": [
                    290,
                    323,
                    320,
                    337
                ],
                "UseBusObject": "off"
            },
            "In2": {
                "AttributesFormatString": "",
                "BlockType": "Inport",
                "BusObject": "BusObject",
                "CompiledPortComplexSignals": {
                    "Enable": [],
                    "Ifaction": [],
                    "Inport": [],
                    "LConn": [],
                    "Outport": 0,
                    "RConn": [],
                    "Reset": [],
                    "State": [],
                    "Trigger": []
                },
                "CompiledPortDataTypes": {
                    "Enable": [],
                    "Ifaction": [],
                    "Inport": [],
                    "LConn": [],
                    "Outport": [
                        "double"
                    ],
                    "RConn": [],
                    "Reset": [],
                    "State": [],
                    "Trigger": []
                },
                "CompiledPortDimensions": {
                    "Enable": [],
                    "Ifaction": [],
                    "Inport": [],
                    "LConn": [],
                    "Outport": [
                        1,
                        1
                    ],
                    "RConn": [],
                    "Reset": [],
                    "State": [],
                    "Trigger": []
                },
                "CompiledPortWidths": {
                    "Enable": [],
                    "Ifaction": [],
                    "Inport": [],
                    "LConn": [],
                    "Outport": 1,
                    "RConn": [],
                    "Reset": [],
                    "State": [],
                    "Trigger": []
                },
                "CompiledSampleTime": [
                    0.1,
                    0
                ],
                "Handle": 122.7943115234375,
                "LineHandles": {
                    "Enable": [],
                    "Ifaction": [],
                    "Inport": [],
                    "LConn": [],
                    "Outport": 315.3701171875,
                    "RConn": [],
                    "Reset": [],
                    "State": [],
                    "Trigger": []
                },
                "Name": "In2",
                "Origin_path": "Rounding1_PP/In2",
                "OutMax": "[]",
                "OutMin": "[]",
                "Path": "Rounding1_PP/In2",
                "Port": "2",
                "PortConnectivity": {
                    "DstBlock": 177.9578857421875,
                    "DstPort": 0,
                    "Position": [
                        325,
                        390
                    ],
                    "SrcBlock": [],
                    "SrcPort": [],
                    "Type": "1"
                },
                "Ports": [
                    0,
                    1,
                    0,
                    0,
                    0,
                    0,
                    0,
                    0,
                    0
                ],
                "Position": [
                    290,
                    383,
                    320,
                    397
                ],
                "UseBusObject": "off"
            },
            "In3": {
                "AttributesFormatString": "",
                "BlockType": "Inport",
                "BusObject": "BusObject",
                "CompiledPortComplexSignals": {
                    "Enable": [],
                    "Ifaction": [],
                    "Inport": [],
                    "LConn": [],
                    "Outport": 0,
                    "RConn": [],
                    "Reset": [],
                    "State": [],
                    "Trigger": []
                },
                "CompiledPortDataTypes": {
                    "Enable": [],
                    "Ifaction": [],
                    "Inport": [],
                    "LConn": [],
                    "Outport": [
                        "double"
                    ],
                    "RConn": [],
                    "Reset": [],
                    "State": [],
                    "Trigger": []
                },
                "CompiledPortDimensions": {
                    "Enable": [],
                    "Ifaction": [],
                    "Inport": [],
                    "LConn": [],
                    "Outport": [
                        1,
                        1
                    ],
                    "RConn": [],
                    "Reset": [],
                    "State": [],
                    "Trigger": []
                },
                "CompiledPortWidths": {
                    "Enable": [],
                    "Ifaction": [],
                    "Inport": [],
                    "LConn": [],
                    "Outport": 1,
                    "RConn": [],
                    "Reset": [],
                    "State": [],
                    "Trigger": []
                },
                "CompiledSampleTime": [
                    0.1,
                    0
                ],
                "Handle": 133.945068359375,
                "LineHandles": {
                    "Enable": [],
                    "Ifaction": [],
                    "Inport": [],
                    "LConn": [],
                    "Outport": 317.3653564453125,
                    "RConn": [],
                    "Reset": [],
                    "State": [],
                    "Trigger": []
                },
                "Name": "In3",
                "Origin_path": "Rounding1_PP/In3",
                "OutMax": "[]",
                "OutMin": "[]",
                "Path": "Rounding1_PP/In3",
                "Port": "3",
                "PortConnectivity": {
                    "DstBlock": 180.665283203125,
                    "DstPort": 0,
                    "Position": [
                        325,
                        450
                    ],
                    "SrcBlock": [],
                    "SrcPort": [],
                    "Type": "1"
                },
                "Ports": [
                    0,
                    1,
                    0,
                    0,
                    0,
                    0,
                    0,
                    0,
                    0
                ],
                "Position": [
                    290,
                    443,
                    320,
                    457
                ],
                "UseBusObject": "off"
            },
            "In4": {
                "AttributesFormatString": "",
                "BlockType": "Inport",
                "BusObject": "BusObject",
                "CompiledPortComplexSignals": {
                    "Enable": [],
                    "Ifaction": [],
                    "Inport": [],
                    "LConn": [],
                    "Outport": 0,
                    "RConn": [],
                    "Reset": [],
                    "State": [],
                    "Trigger": []
                },
                "CompiledPortDataTypes": {
                    "Enable": [],
                    "Ifaction": [],
                    "Inport": [],
                    "LConn": [],
                    "Outport": [
                        "double"
                    ],
                    "RConn": [],
                    "Reset": [],
                    "State": [],
                    "Trigger": []
                },
                "CompiledPortDimensions": {
                    "Enable": [],
                    "Ifaction": [],
                    "Inport": [],
                    "LConn": [],
                    "Outport": [
                        1,
                        1
                    ],
                    "RConn": [],
                    "Reset": [],
                    "State": [],
                    "Trigger": []
                },
                "CompiledPortWidths": {
                    "Enable": [],
                    "Ifaction": [],
                    "Inport": [],
                    "LConn": [],
                    "Outport": 1,
                    "RConn": [],
                    "Reset": [],
                    "State": [],
                    "Trigger": []
                },
                "CompiledSampleTime": [
                    0.1,
                    0
                ],
                "Handle": 156.88720703125,
                "LineHandles": {
                    "Enable": [],
                    "Ifaction": [],
                    "Inport": [],
                    "LConn": [],
                    "Outport": 319.6802978515625,
                    "RConn": [],
                    "Reset": [],
                    "State": [],
                    "Trigger": []
                },
                "Name": "In4",
                "Origin_path": "Rounding1_PP/In4",
                "OutMax": "[]",
                "OutMin": "[]",
                "Path": "Rounding1_PP/In4",
                "Port": "4",
                "PortConnectivity": {
                    "DstBlock": 195.53125,
                    "DstPort": 0,
                    "Position": [
                        325,
                        500
                    ],
                    "SrcBlock": [],
                    "SrcPort": [],
                    "Type": "1"
                },
                "Ports": [
                    0,
                    1,
                    0,
                    0,
                    0,
                    0,
                    0,
                    0,
                    0
                ],
                "Position": [
                    290,
                    493,
                    320,
                    507
                ],
                "UseBusObject": "off"
            },
            "Out1": {
                "AttributesFormatString": "",
                "BlockType": "Outport",
                "BusObject": "BusObject",
                "CompiledPortComplexSignals": {
                    "Enable": [],
                    "Ifaction": [],
                    "Inport": 0,
                    "LConn": [],
                    "Outport": [],
                    "RConn": [],
                    "Reset": [],
                    "State": [],
                    "Trigger": []
                },
                "CompiledPortDataTypes": {
                    "Enable": [],
                    "Ifaction": [],
                    "Inport": [
                        "double"
                    ],
                    "LConn": [],
                    "Outport": [],
                    "RConn": [],
                    "Reset": [],
                    "State": [],
                    "Trigger": []
                },
                "CompiledPortDimensions": {
                    "Enable": [],
                    "Ifaction": [],
                    "Inport": [
                        1,
                        1
                    ],
                    "LConn": [],
                    "Outport": [],
                    "RConn": [],
                    "Reset": [],
                    "State": [],
                    "Trigger": []
                },
                "CompiledPortWidths": {
                    "Enable": [],
                    "Ifaction": [],
                    "Inport": 1,
                    "LConn": [],
                    "Outport": [],
                    "RConn": [],
                    "Reset": [],
                    "State": [],
                    "Trigger": []
                },
                "CompiledSampleTime": [
                    0.1,
                    0
                ],
                "Handle": 286.49560546875,
                "InitialOutput": "[]",
                "LineHandles": {
                    "Enable": [],
                    "Ifaction": [],
                    "Inport": 312.5184326171875,
                    "LConn": [],
                    "Outport": [],
                    "RConn": [],
                    "Reset": [],
                    "State": [],
                    "Trigger": []
                },
                "Name": "Out1",
                "Origin_path": "Rounding1_PP/Out1",
                "OutMax": "[]",
                "OutMin": "[]",
                "OutputWhenDisabled": "held",
                "Path": "Rounding1_PP/Out1",
                "Port": "1",
                "PortConnectivity": {
                    "DstBlock": [],
                    "DstPort": [],
                    "Position": [
                        420,
                        330
                    ],
                    "SrcBlock": 165.8046875,
                    "SrcPort": 0,
                    "Type": "1"
                },
                "Ports": [
                    1,
                    0,
                    0,
                    0,
                    0,
                    0,
                    0,
                    0,
                    0
                ],
                "Position": [
                    425,
                    323,
                    455,
                    337
                ],
                "UseBusObject": "off"
            },
            "Out2": {
                "AttributesFormatString": "",
                "BlockType": "Outport",
                "BusObject": "BusObject",
                "CompiledPortComplexSignals": {
                    "Enable": [],
                    "Ifaction": [],
                    "Inport": 0,
                    "LConn": [],
                    "Outport": [],
                    "RConn": [],
                    "Reset": [],
                    "State": [],
                    "Trigger": []
                },
                "CompiledPortDataTypes": {
                    "Enable": [],
                    "Ifaction": [],
                    "Inport": [
                        "double"
                    ],
                    "LConn": [],
                    "Outport": [],
                    "RConn": [],
                    "Reset": [],
                    "State": [],
                    "Trigger": []
                },
                "CompiledPortDimensions": {
                    "Enable": [],
                    "Ifaction": [],
                    "Inport": [
                        1,
                        1
                    ],
                    "LConn": [],
                    "Outport": [],
                    "RConn": [],
                    "Reset": [],
                    "State": [],
                    "Trigger": []
                },
                "CompiledPortWidths": {
                    "Enable": [],
                    "Ifaction": [],
                    "Inport": 1,
                    "LConn": [],
                    "Outport": [],
                    "RConn": [],
                    "Reset": [],
                    "State": [],
                    "Trigger": []
                },
                "CompiledSampleTime": [
                    0.1,
                    0
                ],
                "Handle": 294.400634765625,
                "InitialOutput": "[]",
                "LineHandles": {
                    "Enable": [],
                    "Ifaction": [],
                    "Inport": 314.8604736328125,
                    "LConn": [],
                    "Outport": [],
                    "RConn": [],
                    "Reset": [],
                    "State": [],
                    "Trigger": []
                },
                "Name": "Out2",
                "Origin_path": "Rounding1_PP/Out2",
                "OutMax": "[]",
                "OutMin": "[]",
                "OutputWhenDisabled": "held",
                "Path": "Rounding1_PP/Out2",
                "Port": "2",
                "PortConnectivity": {
                    "DstBlock": [],
                    "DstPort": [],
                    "Position": [
                        420,
                        390
                    ],
                    "SrcBlock": 177.9578857421875,
                    "SrcPort": 0,
                    "Type": "1"
                },
                "Ports": [
                    1,
                    0,
                    0,
                    0,
                    0,
                    0,
                    0,
                    0,
                    0
                ],
                "Position": [
                    425,
                    383,
                    455,
                    397
                ],
                "UseBusObject": "off"
            },
            "Out3": {
                "AttributesFormatString": "",
                "BlockType": "Outport",
                "BusObject": "BusObject",
                "CompiledPortComplexSignals": {
                    "Enable": [],
                    "Ifaction": [],
                    "Inport": 0,
                    "LConn": [],
                    "Outport": [],
                    "RConn": [],
                    "Reset": [],
                    "State": [],
                    "Trigger": []
                },
                "CompiledPortDataTypes": {
                    "Enable": [],
                    "Ifaction": [],
                    "Inport": [
                        "double"
                    ],
                    "LConn": [],
                    "Outport": [],
                    "RConn": [],
                    "Reset": [],
                    "State": [],
                    "Trigger": []
                },
                "CompiledPortDimensions": {
                    "Enable": [],
                    "Ifaction": [],
                    "Inport": [
                        1,
                        1
                    ],
                    "LConn": [],
                    "Outport": [],
                    "RConn": [],
                    "Reset": [],
                    "State": [],
                    "Trigger": []
                },
                "CompiledPortWidths": {
                    "Enable": [],
                    "Ifaction": [],
                    "Inport": 1,
                    "LConn": [],
                    "Outport": [],
                    "RConn": [],
                    "Reset": [],
                    "State": [],
                    "Trigger": []
                },
                "CompiledSampleTime": [
                    0.1,
                    0
                ],
                "Handle": 295.7020263671875,
                "InitialOutput": "[]",
                "LineHandles": {
                    "Enable": [],
                    "Ifaction": [],
                    "Inport": 316.3624267578125,
                    "LConn": [],
                    "Outport": [],
                    "RConn": [],
                    "Reset": [],
                    "State": [],
                    "Trigger": []
                },
                "Name": "Out3",
                "Origin_path": "Rounding1_PP/Out3",
                "OutMax": "[]",
                "OutMin": "[]",
                "OutputWhenDisabled": "held",
                "Path": "Rounding1_PP/Out3",
                "Port": "3",
                "PortConnectivity": {
                    "DstBlock": [],
                    "DstPort": [],
                    "Position": [
                        420,
                        450
                    ],
                    "SrcBlock": 180.665283203125,
                    "SrcPort": 0,
                    "Type": "1"
                },
                "Ports": [
                    1,
                    0,
                    0,
                    0,
                    0,
                    0,
                    0,
                    0,
                    0
                ],
                "Position": [
                    425,
                    443,
                    455,
                    457
                ],
                "UseBusObject": "off"
            },
            "Out4": {
                "AttributesFormatString": "",
                "BlockType": "Outport",
                "BusObject": "BusObject",
                "CompiledPortComplexSignals": {
                    "Enable": [],
                    "Ifaction": [],
                    "Inport": 0,
                    "LConn": [],
                    "Outport": [],
                    "RConn": [],
                    "Reset": [],
                    "State": [],
                    "Trigger": []
                },
                "CompiledPortDataTypes": {
                    "Enable": [],
                    "Ifaction": [],
                    "Inport": [
                        "double"
                    ],
                    "LConn": [],
                    "Outport": [],
                    "RConn": [],
                    "Reset": [],
                    "State": [],
                    "Trigger": []
                },
                "CompiledPortDimensions": {
                    "Enable": [],
                    "Ifaction": [],
                    "Inport": [
                        1,
                        1
                    ],
                    "LConn": [],
                    "Outport": [],
                    "RConn": [],
                    "Reset": [],
                    "State": [],
                    "Trigger": []
                },
                "CompiledPortWidths": {
                    "Enable": [],
                    "Ifaction": [],
                    "Inport": 1,
                    "LConn": [],
                    "Outport": [],
                    "RConn": [],
                    "Reset": [],
                    "State": [],
                    "Trigger": []
                },
                "CompiledSampleTime": [
                    0.1,
                    0
                ],
                "Handle": 310.775634765625,
                "InitialOutput": "[]",
                "LineHandles": {
                    "Enable": [],
                    "Ifaction": [],
                    "Inport": 318.5184326171875,
                    "LConn": [],
                    "Outport": [],
                    "RConn": [],
                    "Reset": [],
                    "State": [],
                    "Trigger": []
                },
                "Name": "Out4",
                "Origin_path": "Rounding1_PP/Out4",
                "OutMax": "[]",
                "OutMin": "[]",
                "OutputWhenDisabled": "held",
                "Path": "Rounding1_PP/Out4",
                "Port": "4",
                "PortConnectivity": {
                    "DstBlock": [],
                    "DstPort": [],
                    "Position": [
                        420,
                        500
                    ],
                    "SrcBlock": 195.53125,
                    "SrcPort": 0,
                    "Type": "1"
                },
                "Ports": [
                    1,
                    0,
                    0,
                    0,
                    0,
                    0,
                    0,
                    0,
                    0
                ],
                "Position": [
                    425,
                    493,
                    455,
                    507
                ],
                "UseBusObject": "off"
            },
            "Rounding_newline_Function": {
                "AttributesFormatString": "",
                "BlockType": "Rounding",
                "CompiledPortComplexSignals": {
                    "Enable": [],
                    "Ifaction": [],
                    "Inport": 0,
                    "LConn": [],
                    "Outport": 0,
                    "RConn": [],
                    "Reset": [],
                    "State": [],
                    "Trigger": []
                },
                "CompiledPortDataTypes": {
                    "Enable": [],
                    "Ifaction": [],
                    "Inport": [
                        "double"
                    ],
                    "LConn": [],
                    "Outport": [
                        "double"
                    ],
                    "RConn": [],
                    "Reset": [],
                    "State": [],
                    "Trigger": []
                },
                "CompiledPortDimensions": {
                    "Enable": [],
                    "Ifaction": [],
                    "Inport": [
                        1,
                        1
                    ],
                    "LConn": [],
                    "Outport": [
                        1,
                        1
                    ],
                    "RConn": [],
                    "Reset": [],
                    "State": [],
                    "Trigger": []
                },
                "CompiledPortWidths": {
                    "Enable": [],
                    "Ifaction": [],
                    "Inport": 1,
                    "LConn": [],
                    "Outport": 1,
                    "RConn": [],
                    "Reset": [],
                    "State": [],
                    "Trigger": []
                },
                "CompiledSampleTime": [
                    0.1,
                    0
                ],
                "Handle": 165.8046875,
                "LineHandles": {
                    "Enable": [],
                    "Ifaction": [],
                    "Inport": 311.3594970703125,
                    "LConn": [],
                    "Outport": 312.5184326171875,
                    "RConn": [],
                    "Reset": [],
                    "State": [],
                    "Trigger": []
                },
                "Name": "Rounding_newline_Function",
                "Operator": "floor",
                "Origin_path": "Rounding1_PP/Rounding_newline_Function",
                "Path": "Rounding1_PP/Rounding_newline_Function",
                "PortConnectivity": [
                    {
                        "DstBlock": [],
                        "DstPort": [],
                        "Position": [
                            360,
                            330
                        ],
                        "SrcBlock": 118.9732666015625,
                        "SrcPort": 0,
                        "Type": "1"
                    },
                    {
                        "DstBlock": 286.49560546875,
                        "DstPort": 0,
                        "Position": [
                            400,
                            330
                        ],
                        "SrcBlock": [],
                        "SrcPort": [],
                        "Type": "1"
                    }
                ],
                "Ports": [
                    1,
                    1,
                    0,
                    0,
                    0,
                    0,
                    0,
                    0,
                    0
                ],
                "Position": [
                    365,
                    315,
                    395,
                    345
                ],
                "SampleTime": "-1"
            },
            "Rounding_newline_Function1": {
                "AttributesFormatString": "",
                "BlockType": "Rounding",
                "CompiledPortComplexSignals": {
                    "Enable": [],
                    "Ifaction": [],
                    "Inport": 0,
                    "LConn": [],
                    "Outport": 0,
                    "RConn": [],
                    "Reset": [],
                    "State": [],
                    "Trigger": []
                },
                "CompiledPortDataTypes": {
                    "Enable": [],
                    "Ifaction": [],
                    "Inport": [
                        "double"
                    ],
                    "LConn": [],
                    "Outport": [
                        "double"
                    ],
                    "RConn": [],
                    "Reset": [],
                    "State": [],
                    "Trigger": []
                },
                "CompiledPortDimensions": {
                    "Enable": [],
                    "Ifaction": [],
                    "Inport": [
                        1,
                        1
                    ],
                    "LConn": [],
                    "Outport": [
                        1,
                        1
                    ],
                    "RConn": [],
                    "Reset": [],
                    "State": [],
                    "Trigger": []
                },
                "CompiledPortWidths": {
                    "Enable": [],
                    "Ifaction": [],
                    "Inport": 1,
                    "LConn": [],
                    "Outport": 1,
                    "RConn": [],
                    "Reset": [],
                    "State": [],
                    "Trigger": []
                },
                "CompiledSampleTime": [
                    0.1,
                    0
                ],
                "Handle": 177.9578857421875,
                "LineHandles": {
                    "Enable": [],
                    "Ifaction": [],
                    "Inport": 315.3701171875,
                    "LConn": [],
                    "Outport": 314.8604736328125,
                    "RConn": [],
                    "Reset": [],
                    "State": [],
                    "Trigger": []
                },
                "Name": "Rounding_newline_Function1",
                "Operator": "ceil",
                "Origin_path": "Rounding1_PP/Rounding_newline_Function1",
                "Path": "Rounding1_PP/Rounding_newline_Function1",
                "PortConnectivity": [
                    {
                        "DstBlock": [],
                        "DstPort": [],
                        "Position": [
                            360,
                            390
                        ],
                        "SrcBlock": 122.7943115234375,
                        "SrcPort": 0,
                        "Type": "1"
                    },
                    {
                        "DstBlock": 294.400634765625,
                        "DstPort": 0,
                        "Position": [
                            400,
                            390
                        ],
                        "SrcBlock": [],
                        "SrcPort": [],
                        "Type": "1"
                    }
                ],
                "Ports": [
                    1,
                    1,
                    0,
                    0,
                    0,
                    0,
                    0,
                    0,
                    0
                ],
                "Position": [
                    365,
                    375,
                    395,
                    405
                ],
                "SampleTime": "-1"
            },
            "Rounding_newline_Function2": {
                "AttributesFormatString": "",
                "BlockType": "Rounding",
                "CompiledPortComplexSignals": {
                    "Enable": [],
                    "Ifaction": [],
                    "Inport": 0,
                    "LConn": [],
                    "Outport": 0,
                    "RConn": [],
                    "Reset": [],
                    "State": [],
                    "Trigger": []
                },
                "CompiledPortDataTypes": {
                    "Enable": [],
                    "Ifaction": [],
                    "Inport": [
                        "double"
                    ],
                    "LConn": [],
                    "Outport": [
                        "double"
                    ],
                    "RConn": [],
                    "Reset": [],
                    "State": [],
                    "Trigger": []
                },
                "CompiledPortDimensions": {
                    "Enable": [],
                    "Ifaction": [],
                    "Inport": [
                        1,
                        1
                    ],
                    "LConn": [],
                    "Outport": [
                        1,
                        1
                    ],
                    "RConn": [],
                    "Reset": [],
                    "State": [],
                    "Trigger": []
                },
                "CompiledPortWidths": {
                    "Enable": [],
                    "Ifaction": [],
                    "Inport": 1,
                    "LConn": [],
                    "Outport": 1,
                    "RConn": [],
                    "Reset": [],
                    "State": [],
                    "Trigger": []
                },
                "CompiledSampleTime": [
                    0.1,
                    0
                ],
                "Handle": 180.665283203125,
                "LineHandles": {
                    "Enable": [],
                    "Ifaction": [],
                    "Inport": 317.3653564453125,
                    "LConn": [],
                    "Outport": 316.3624267578125,
                    "RConn": [],
                    "Reset": [],
                    "State": [],
                    "Trigger": []
                },
                "Name": "Rounding_newline_Function2",
                "Operator": "round",
                "Origin_path": "Rounding1_PP/Rounding_newline_Function2",
                "Path": "Rounding1_PP/Rounding_newline_Function2",
                "PortConnectivity": [
                    {
                        "DstBlock": [],
                        "DstPort": [],
                        "Position": [
                            360,
                            450
                        ],
                        "SrcBlock": 133.945068359375,
                        "SrcPort": 0,
                        "Type": "1"
                    },
                    {
                        "DstBlock": 295.7020263671875,
                        "DstPort": 0,
                        "Position": [
                            400,
                            450
                        ],
                        "SrcBlock": [],
                        "SrcPort": [],
                        "Type": "1"
                    }
                ],
                "Ports": [
                    1,
                    1,
                    0,
                    0,
                    0,
                    0,
                    0,
                    0,
                    0
                ],
                "Position": [
                    365,
                    435,
                    395,
                    465
                ],
                "SampleTime": "-1"
            },
            "Rounding_newline_Function3": {
                "AttributesFormatString": "",
                "BlockType": "Rounding",
                "CompiledPortComplexSignals": {
                    "Enable": [],
                    "Ifaction": [],
                    "Inport": 0,
                    "LConn": [],
                    "Outport": 0,
                    "RConn": [],
                    "Reset": [],
                    "State": [],
                    "Trigger": []
                },
                "CompiledPortDataTypes": {
                    "Enable": [],
                    "Ifaction": [],
                    "Inport": [
                        "double"
                    ],
                    "LConn": [],
                    "Outport": [
                        "double"
                    ],
                    "RConn": [],
                    "Reset": [],
                    "State": [],
                    "Trigger": []
                },
                "CompiledPortDimensions": {
                    "Enable": [],
                    "Ifaction": [],
                    "Inport": [
                        1,
                        1
                    ],
                    "LConn": [],
                    "Outport": [
                        1,
                        1
                    ],
                    "RConn": [],
                    "Reset": [],
                    "State": [],
                    "Trigger": []
                },
                "CompiledPortWidths": {
                    "Enable": [],
                    "Ifaction": [],
                    "Inport": 1,
                    "LConn": [],
                    "Outport": 1,
                    "RConn": [],
                    "Reset": [],
                    "State": [],
                    "Trigger": []
                },
                "CompiledSampleTime": [
                    0.1,
                    0
                ],
                "Handle": 195.53125,
                "LineHandles": {
                    "Enable": [],
                    "Ifaction": [],
                    "Inport": 319.6802978515625,
                    "LConn": [],
                    "Outport": 318.5184326171875,
                    "RConn": [],
                    "Reset": [],
                    "State": [],
                    "Trigger": []
                },
                "Name": "Rounding_newline_Function3",
                "Operator": "fix",
                "Origin_path": "Rounding1_PP/Rounding_newline_Function3",
                "Path": "Rounding1_PP/Rounding_newline_Function3",
                "PortConnectivity": [
                    {
                        "DstBlock": [],
                        "DstPort": [],
                        "Position": [
                            360,
                            500
                        ],
                        "SrcBlock": 156.88720703125,
                        "SrcPort": 0,
                        "Type": "1"
                    },
                    {
                        "DstBlock": 310.775634765625,
                        "DstPort": 0,
                        "Position": [
                            400,
                            500
                        ],
                        "SrcBlock": [],
                        "SrcPort": [],
                        "Type": "1"
                    }
                ],
                "Ports": [
                    1,
                    1,
                    0,
                    0,
                    0,
                    0,
                    0,
                    0,
                    0
                ],
                "Position": [
                    365,
                    485,
                    395,
                    515
                ],
                "SampleTime": "-1"
            }
        },
        "Handle": 9.95458984375,
        "Name": "Rounding1_PP",
        "Origin_path": "Rounding1_PP",
        "Path": "Rounding1_PP"
    },
    "meta": {
        "Declarations": {
            "Enumerations": []
        },
        "date": "20-Nov-2020",
        "file_path": "/Users/ktrinh/cocosim/cocosim_github/cocosim_tests/Simulink/unitTests/Rounding/Rounding1_PP.slx",
        "sampleTime": 0.1
    }
}
