{
    "MultiportSwitch_TestGen13_PP": {
        "AllCompiledSampleTimes": [
            [
                0.2,
                0
            ]
        ],
        "BlockType": "block_diagram",
        "CompiledSampleTime": [
            0.2,
            0
        ],
        "Content": {
            "In1": {
                "AttributesFormatString": "",
                "BlockType": "Inport",
                "BusObject": "BusObject",
                "CompiledPortComplexSignals": {
                    "Enable": [],
                    "Ifaction": [],
                    "Inport": [],
                    "LConn": [],
                    "Outport": 0,
                    "RConn": [],
                    "Reset": [],
                    "State": [],
                    "Trigger": []
                },
                "CompiledPortDataTypes": {
                    "Enable": [],
                    "Ifaction": [],
                    "Inport": [],
                    "LConn": [],
                    "Outport": [
                        "double"
                    ],
                    "RConn": [],
                    "Reset": [],
                    "State": [],
                    "Trigger": []
                },
                "CompiledPortDimensions": {
                    "Enable": [],
                    "Ifaction": [],
                    "Inport": [],
                    "LConn": [],
                    "Outport": [
                        1,
                        1
                    ],
                    "RConn": [],
                    "Reset": [],
                    "State": [],
                    "Trigger": []
                },
                "CompiledPortWidths": {
                    "Enable": [],
                    "Ifaction": [],
                    "Inport": [],
                    "LConn": [],
                    "Outport": 1,
                    "RConn": [],
                    "Reset": [],
                    "State": [],
                    "Trigger": []
                },
                "CompiledSampleTime": [
                    0.2,
                    0
                ],
                "Handle": 112.957275390625,
                "LineHandles": {
                    "Enable": [],
                    "Ifaction": [],
                    "Inport": [],
                    "LConn": [],
                    "Outport": 181.738525390625,
                    "RConn": [],
                    "Reset": [],
                    "State": [],
                    "Trigger": []
                },
                "Name": "In1",
                "Origin_path": "MultiportSwitch_TestGen13_PP/In1",
                "OutMax": "2",
                "OutMin": "1",
                "Path": "MultiportSwitch_TestGen13_PP/In1",
                "Port": "1",
                "PortConnectivity": {
                    "DstBlock": 133.8487548828125,
                    "DstPort": 0,
                    "Position": [
                        110,
                        145
                    ],
                    "SrcBlock": [],
                    "SrcPort": [],
                    "Type": "1"
                },
                "Ports": [
                    0,
                    1,
                    0,
                    0,
                    0,
                    0,
                    0,
                    0,
                    0
                ],
                "Position": [
                    75,
                    138,
                    105,
                    152
                ],
                "UseBusObject": "off"
            },
            "In2": {
                "AttributesFormatString": "",
                "BlockType": "Inport",
                "BusObject": "BusObject",
                "CompiledPortComplexSignals": {
                    "Enable": [],
                    "Ifaction": [],
                    "Inport": [],
                    "LConn": [],
                    "Outport": 0,
                    "RConn": [],
                    "Reset": [],
                    "State": [],
                    "Trigger": []
                },
                "CompiledPortDataTypes": {
                    "Enable": [],
                    "Ifaction": [],
                    "Inport": [],
                    "LConn": [],
                    "Outport": [
                        "double"
                    ],
                    "RConn": [],
                    "Reset": [],
                    "State": [],
                    "Trigger": []
                },
                "CompiledPortDimensions": {
                    "Enable": [],
                    "Ifaction": [],
                    "Inport": [],
                    "LConn": [],
                    "Outport": [
                        2,
                        1,
                        5
                    ],
                    "RConn": [],
                    "Reset": [],
                    "State": [],
                    "Trigger": []
                },
                "CompiledPortWidths": {
                    "Enable": [],
                    "Ifaction": [],
                    "Inport": [],
                    "LConn": [],
                    "Outport": 5,
                    "RConn": [],
                    "Reset": [],
                    "State": [],
                    "Trigger": []
                },
                "CompiledSampleTime": [
                    0.2,
                    0
                ],
                "Handle": 113.53662109375,
                "LineHandles": {
                    "Enable": [],
                    "Ifaction": [],
                    "Inport": [],
                    "LConn": [],
                    "Outport": 179.7242431640625,
                    "RConn": [],
                    "Reset": [],
                    "State": [],
                    "Trigger": []
                },
                "Name": "In2",
                "Origin_path": "MultiportSwitch_TestGen13_PP/In2",
                "OutMax": "[]",
                "OutMin": "[]",
                "Path": "MultiportSwitch_TestGen13_PP/In2",
                "Port": "2",
                "PortConnectivity": {
                    "DstBlock": 115.71142578125,
                    "DstPort": 1,
                    "Position": [
                        110,
                        195
                    ],
                    "SrcBlock": [],
                    "SrcPort": [],
                    "Type": "1"
                },
                "Ports": [
                    0,
                    1,
                    0,
                    0,
                    0,
                    0,
                    0,
                    0,
                    0
                ],
                "Position": [
                    75,
                    188,
                    105,
                    202
                ],
                "UseBusObject": "off"
            },
            "Out1": {
                "AttributesFormatString": "",
                "BlockType": "Outport",
                "BusObject": "BusObject",
                "CompiledPortComplexSignals": {
                    "Enable": [],
                    "Ifaction": [],
                    "Inport": 0,
                    "LConn": [],
                    "Outport": [],
                    "RConn": [],
                    "Reset": [],
                    "State": [],
                    "Trigger": []
                },
                "CompiledPortDataTypes": {
                    "Enable": [],
                    "Ifaction": [],
                    "Inport": [
                        "double"
                    ],
                    "LConn": [],
                    "Outport": [],
                    "RConn": [],
                    "Reset": [],
                    "State": [],
                    "Trigger": []
                },
                "CompiledPortDimensions": {
                    "Enable": [],
                    "Ifaction": [],
                    "Inport": [
                        2,
                        1,
                        1
                    ],
                    "LConn": [],
                    "Outport": [],
                    "RConn": [],
                    "Reset": [],
                    "State": [],
                    "Trigger": []
                },
                "CompiledPortWidths": {
                    "Enable": [],
                    "Ifaction": [],
                    "Inport": 1,
                    "LConn": [],
                    "Outport": [],
                    "RConn": [],
                    "Reset": [],
                    "State": [],
                    "Trigger": []
                },
                "CompiledSampleTime": [
                    0.2,
                    0
                ],
                "Handle": 177.9327392578125,
                "InitialOutput": "[]",
                "LineHandles": {
                    "Enable": [],
                    "Ifaction": [],
                    "Inport": 180.74365234375,
                    "LConn": [],
                    "Outport": [],
                    "RConn": [],
                    "Reset": [],
                    "State": [],
                    "Trigger": []
                },
                "Name": "Out1",
                "Origin_path": "MultiportSwitch_TestGen13_PP/Out1",
                "OutMax": "[]",
                "OutMin": "[]",
                "OutputWhenDisabled": "held",
                "Path": "MultiportSwitch_TestGen13_PP/Out1",
                "Port": "1",
                "PortConnectivity": {
                    "DstBlock": [],
                    "DstPort": [],
                    "Position": [
                        250,
                        170
                    ],
                    "SrcBlock": 115.71142578125,
                    "SrcPort": 0,
                    "Type": "1"
                },
                "Ports": [
                    1,
                    0,
                    0,
                    0,
                    0,
                    0,
                    0,
                    0,
                    0
                ],
                "Position": [
                    255,
                    163,
                    285,
                    177
                ],
                "UseBusObject": "off"
            },
            "P": {
                "AllowDiffInputSizes": "off",
                "AttributesFormatString": "",
                "BlockType": "MultiPortSwitch",
                "CompiledPortComplexSignals": {
                    "Enable": [],
                    "Ifaction": [],
                    "Inport": [
                        0,
                        0
                    ],
                    "LConn": [],
                    "Outport": 0,
                    "RConn": [],
                    "Reset": [],
                    "State": [],
                    "Trigger": []
                },
                "CompiledPortDataTypes": {
                    "Enable": [],
                    "Ifaction": [],
                    "Inport": [
                        "double",
                        "double"
                    ],
                    "LConn": [],
                    "Outport": [
                        "double"
                    ],
                    "RConn": [],
                    "Reset": [],
                    "State": [],
                    "Trigger": []
                },
                "CompiledPortDimensions": {
                    "Enable": [],
                    "Ifaction": [],
                    "Inport": [
                        1,
                        1,
                        2,
                        1,
                        5
                    ],
                    "LConn": [],
                    "Outport": [
                        2,
                        1,
                        1
                    ],
                    "RConn": [],
                    "Reset": [],
                    "State": [],
                    "Trigger": []
                },
                "CompiledPortWidths": {
                    "Enable": [],
                    "Ifaction": [],
                    "Inport": [
                        1,
                        5
                    ],
                    "LConn": [],
                    "Outport": 1,
                    "RConn": [],
                    "Reset": [],
                    "State": [],
                    "Trigger": []
                },
                "CompiledSampleTime": [
                    0.2,
                    0
                ],
                "DataPortForDefault": "Additional data port",
                "DataPortIndices": "{1,2,3}",
                "DataPortOrder": "One-based contiguous",
                "Handle": 115.71142578125,
                "Inputs": "1",
                "LineHandles": {
                    "Enable": [],
                    "Ifaction": [],
                    "Inport": [
                        182.593017578125,
                        179.7242431640625
                    ],
                    "LConn": [],
                    "Outport": 180.74365234375,
                    "RConn": [],
                    "Reset": [],
                    "State": [],
                    "Trigger": []
                },
                "Name": "P",
                "Origin_path": "MultiportSwitch_TestGen13_PP/P",
                "OutMax": "[]",
                "OutMin": "[]",
                "Path": "MultiportSwitch_TestGen13_PP/P",
                "PortConnectivity": [
                    {
                        "DstBlock": [],
                        "DstPort": [],
                        "Position": [
                            160,
                            145
                        ],
                        "SrcBlock": 133.8487548828125,
                        "SrcPort": 0,
                        "Type": "1"
                    },
                    {
                        "DstBlock": [],
                        "DstPort": [],
                        "Position": [
                            160,
                            195
                        ],
                        "SrcBlock": 113.53662109375,
                        "SrcPort": 0,
                        "Type": "2"
                    },
                    {
                        "DstBlock": 177.9327392578125,
                        "DstPort": 0,
                        "Position": [
                            200,
                            170
                        ],
                        "SrcBlock": [],
                        "SrcPort": [],
                        "Type": "1"
                    }
                ],
                "Ports": [
                    2,
                    1,
                    0,
                    0,
                    0,
                    0,
                    0,
                    0,
                    0
                ],
                "Position": [
                    165,
                    120,
                    195,
                    220
                ],
                "RndMeth": "Floor",
                "SaturateOnIntegerOverflow": "off"
            },
            "Satur": {
                "AttributesFormatString": "",
                "BlockType": "SubSystem",
                "CompiledPortComplexSignals": {
                    "Enable": [],
                    "Ifaction": [],
                    "Inport": 0,
                    "LConn": [],
                    "Outport": 0,
                    "RConn": [],
                    "Reset": [],
                    "State": [],
                    "Trigger": []
                },
                "CompiledPortDataTypes": {
                    "Enable": [],
                    "Ifaction": [],
                    "Inport": [
                        "double"
                    ],
                    "LConn": [],
                    "Outport": [
                        "double"
                    ],
                    "RConn": [],
                    "Reset": [],
                    "State": [],
                    "Trigger": []
                },
                "CompiledPortDimensions": {
                    "Enable": [],
                    "Ifaction": [],
                    "Inport": [
                        1,
                        1
                    ],
                    "LConn": [],
                    "Outport": [
                        1,
                        1
                    ],
                    "RConn": [],
                    "Reset": [],
                    "State": [],
                    "Trigger": []
                },
                "CompiledPortWidths": {
                    "Enable": [],
                    "Ifaction": [],
                    "Inport": 1,
                    "LConn": [],
                    "Outport": 1,
                    "RConn": [],
                    "Reset": [],
                    "State": [],
                    "Trigger": []
                },
                "CompiledSampleTime": [
                    0.2,
                    0
                ],
                "Content": {
                    "In": {
                        "AttributesFormatString": "",
                        "BlockType": "Inport",
                        "BusObject": "BusObject",
                        "CompiledPortComplexSignals": {
                            "Enable": [],
                            "Ifaction": [],
                            "Inport": [],
                            "LConn": [],
                            "Outport": 0,
                            "RConn": [],
                            "Reset": [],
                            "State": [],
                            "Trigger": []
                        },
                        "CompiledPortDataTypes": {
                            "Enable": [],
                            "Ifaction": [],
                            "Inport": [],
                            "LConn": [],
                            "Outport": [
                                "double"
                            ],
                            "RConn": [],
                            "Reset": [],
                            "State": [],
                            "Trigger": []
                        },
                        "CompiledPortDimensions": {
                            "Enable": [],
                            "Ifaction": [],
                            "Inport": [],
                            "LConn": [],
                            "Outport": [
                                1,
                                1
                            ],
                            "RConn": [],
                            "Reset": [],
                            "State": [],
                            "Trigger": []
                        },
                        "CompiledPortWidths": {
                            "Enable": [],
                            "Ifaction": [],
                            "Inport": [],
                            "LConn": [],
                            "Outport": 1,
                            "RConn": [],
                            "Reset": [],
                            "State": [],
                            "Trigger": []
                        },
                        "CompiledSampleTime": [
                            0.2,
                            0
                        ],
                        "Handle": 195.547607421875,
                        "LineHandles": {
                            "Enable": [],
                            "Ifaction": [],
                            "Inport": [],
                            "LConn": [],
                            "Outport": 158257.00732421875,
                            "RConn": [],
                            "Reset": [],
                            "State": [],
                            "Trigger": []
                        },
                        "Name": "In",
                        "Origin_path": "MultiportSwitch_TestGen13_PP/Satur/In",
                        "OutMax": "[]",
                        "OutMin": "[]",
                        "Path": "MultiportSwitch_TestGen13_PP/Satur/In",
                        "Port": "1",
                        "PortConnectivity": {
                            "DstBlock": 158253.00708007812,
                            "DstPort": 1,
                            "Position": [
                                60,
                                110
                            ],
                            "SrcBlock": [],
                            "SrcPort": [],
                            "Type": "1"
                        },
                        "Ports": [
                            0,
                            1,
                            0,
                            0,
                            0,
                            0,
                            0,
                            0,
                            0
                        ],
                        "Position": [
                            25,
                            103,
                            55,
                            117
                        ],
                        "UseBusObject": "off"
                    },
                    "Out": {
                        "AttributesFormatString": "",
                        "BlockType": "Outport",
                        "BusObject": "BusObject",
                        "CompiledPortComplexSignals": {
                            "Enable": [],
                            "Ifaction": [],
                            "Inport": 0,
                            "LConn": [],
                            "Outport": [],
                            "RConn": [],
                            "Reset": [],
                            "State": [],
                            "Trigger": []
                        },
                        "CompiledPortDataTypes": {
                            "Enable": [],
                            "Ifaction": [],
                            "Inport": [
                                "double"
                            ],
                            "LConn": [],
                            "Outport": [],
                            "RConn": [],
                            "Reset": [],
                            "State": [],
                            "Trigger": []
                        },
                        "CompiledPortDimensions": {
                            "Enable": [],
                            "Ifaction": [],
                            "Inport": [
                                1,
                                1
                            ],
                            "LConn": [],
                            "Outport": [],
                            "RConn": [],
                            "Reset": [],
                            "State": [],
                            "Trigger": []
                        },
                        "CompiledPortWidths": {
                            "Enable": [],
                            "Ifaction": [],
                            "Inport": 1,
                            "LConn": [],
                            "Outport": [],
                            "RConn": [],
                            "Reset": [],
                            "State": [],
                            "Trigger": []
                        },
                        "CompiledSampleTime": [
                            0.2,
                            0
                        ],
                        "Handle": 158255.00708007812,
                        "InitialOutput": "[]",
                        "LineHandles": {
                            "Enable": [],
                            "Ifaction": [],
                            "Inport": 158256.00708007812,
                            "LConn": [],
                            "Outport": [],
                            "RConn": [],
                            "Reset": [],
                            "State": [],
                            "Trigger": []
                        },
                        "Name": "Out",
                        "Origin_path": "MultiportSwitch_TestGen13_PP/Satur/Out",
                        "OutMax": "[]",
                        "OutMin": "[]",
                        "OutputWhenDisabled": "held",
                        "Path": "MultiportSwitch_TestGen13_PP/Satur/Out",
                        "Port": "1",
                        "PortConnectivity": {
                            "DstBlock": [],
                            "DstPort": [],
                            "Position": [
                                245,
                                115
                            ],
                            "SrcBlock": 196.8116455078125,
                            "SrcPort": 0,
                            "Type": "1"
                        },
                        "Ports": [
                            1,
                            0,
                            0,
                            0,
                            0,
                            0,
                            0,
                            0,
                            0
                        ],
                        "Position": [
                            250,
                            108,
                            280,
                            122
                        ],
                        "UseBusObject": "off"
                    },
                    "lower": {
                        "AttributesFormatString": "",
                        "BlockType": "MinMax",
                        "CompiledPortComplexSignals": {
                            "Enable": [],
                            "Ifaction": [],
                            "Inport": [
                                0,
                                0
                            ],
                            "LConn": [],
                            "Outport": 0,
                            "RConn": [],
                            "Reset": [],
                            "State": [],
                            "Trigger": []
                        },
                        "CompiledPortDataTypes": {
                            "Enable": [],
                            "Ifaction": [],
                            "Inport": [
                                "double",
                                "double"
                            ],
                            "LConn": [],
                            "Outport": [
                                "double"
                            ],
                            "RConn": [],
                            "Reset": [],
                            "State": [],
                            "Trigger": []
                        },
                        "CompiledPortDimensions": {
                            "Enable": [],
                            "Ifaction": [],
                            "Inport": [
                                1,
                                1,
                                1,
                                1
                            ],
                            "LConn": [],
                            "Outport": [
                                1,
                                1
                            ],
                            "RConn": [],
                            "Reset": [],
                            "State": [],
                            "Trigger": []
                        },
                        "CompiledPortWidths": {
                            "Enable": [],
                            "Ifaction": [],
                            "Inport": [
                                1,
                                1
                            ],
                            "LConn": [],
                            "Outport": 1,
                            "RConn": [],
                            "Reset": [],
                            "State": [],
                            "Trigger": []
                        },
                        "CompiledSampleTime": [
                            0.2,
                            0
                        ],
                        "Function": "max",
                        "Handle": 196.8116455078125,
                        "InputSameDT": "off",
                        "Inputs": "2",
                        "LineHandles": {
                            "Enable": [],
                            "Ifaction": [],
                            "Inport": [
                                158259.00732421875,
                                158258.00732421875
                            ],
                            "LConn": [],
                            "Outport": 158256.00708007812,
                            "RConn": [],
                            "Reset": [],
                            "State": [],
                            "Trigger": []
                        },
                        "LockScale": "off",
                        "Name": "lower",
                        "Origin_path": "MultiportSwitch_TestGen13_PP/Satur/lower",
                        "OutDataTypeStr": "Inherit: Inherit via back propagation",
                        "OutMax": "[]",
                        "OutMin": "[]",
                        "Path": "MultiportSwitch_TestGen13_PP/Satur/lower",
                        "PortConnectivity": [
                            {
                                "DstBlock": [],
                                "DstPort": [],
                                "Position": [
                                    190,
                                    105
                                ],
                                "SrcBlock": 158253.00708007812,
                                "SrcPort": 0,
                                "Type": "1"
                            },
                            {
                                "DstBlock": [],
                                "DstPort": [],
                                "Position": [
                                    190,
                                    120
                                ],
                                "SrcBlock": 158252.00708007812,
                                "SrcPort": 0,
                                "Type": "2"
                            },
                            {
                                "DstBlock": 158255.00708007812,
                                "DstPort": 0,
                                "Position": [
                                    230,
                                    115
                                ],
                                "SrcBlock": [],
                                "SrcPort": [],
                                "Type": "1"
                            }
                        ],
                        "Ports": [
                            2,
                            1,
                            0,
                            0,
                            0,
                            0,
                            0,
                            0,
                            0
                        ],
                        "Position": [
                            195,
                            97,
                            225,
                            128
                        ],
                        "RndMeth": "Floor",
                        "SampleTime": "-1",
                        "SaturateOnIntegerOverflow": "off",
                        "ZeroCross": "on"
                    },
                    "lower_limit": {
                        "AttributesFormatString": "",
                        "BlockType": "Constant",
                        "CompiledPortComplexSignals": {
                            "Enable": [],
                            "Ifaction": [],
                            "Inport": [],
                            "LConn": [],
                            "Outport": 0,
                            "RConn": [],
                            "Reset": [],
                            "State": [],
                            "Trigger": []
                        },
                        "CompiledPortDataTypes": {
                            "Enable": [],
                            "Ifaction": [],
                            "Inport": [],
                            "LConn": [],
                            "Outport": [
                                "double"
                            ],
                            "RConn": [],
                            "Reset": [],
                            "State": [],
                            "Trigger": []
                        },
                        "CompiledPortDimensions": {
                            "Enable": [],
                            "Ifaction": [],
                            "Inport": [],
                            "LConn": [],
                            "Outport": [
                                1,
                                1
                            ],
                            "RConn": [],
                            "Reset": [],
                            "State": [],
                            "Trigger": []
                        },
                        "CompiledPortWidths": {
                            "Enable": [],
                            "Ifaction": [],
                            "Inport": [],
                            "LConn": [],
                            "Outport": 1,
                            "RConn": [],
                            "Reset": [],
                            "State": [],
                            "Trigger": []
                        },
                        "CompiledSampleTime": [
                            0.2,
                            0
                        ],
                        "FramePeriod": "inf",
                        "Handle": 158252.00708007812,
                        "LineHandles": {
                            "Enable": [],
                            "Ifaction": [],
                            "Inport": [],
                            "LConn": [],
                            "Outport": 158258.00732421875,
                            "RConn": [],
                            "Reset": [],
                            "State": [],
                            "Trigger": []
                        },
                        "LockScale": "off",
                        "Name": "lower_limit",
                        "Origin_path": "MultiportSwitch_TestGen13_PP/Satur/lower_limit",
                        "OutDataTypeStr": "Inherit: Inherit via back propagation",
                        "OutMax": "[]",
                        "OutMin": "[]",
                        "Path": "MultiportSwitch_TestGen13_PP/Satur/lower_limit",
                        "PortConnectivity": {
                            "DstBlock": 196.8116455078125,
                            "DstPort": 1,
                            "Position": [
                                60,
                                155
                            ],
                            "SrcBlock": [],
                            "SrcPort": [],
                            "Type": "1"
                        },
                        "Ports": [
                            0,
                            1,
                            0,
                            0,
                            0,
                            0,
                            0,
                            0,
                            0
                        ],
                        "Position": [
                            25,
                            140,
                            55,
                            170
                        ],
                        "SampleTime": "-1",
                        "Value": "1",
                        "VectorParams1D": "on"
                    },
                    "upper": {
                        "AttributesFormatString": "",
                        "BlockType": "MinMax",
                        "CompiledPortComplexSignals": {
                            "Enable": [],
                            "Ifaction": [],
                            "Inport": [
                                0,
                                0
                            ],
                            "LConn": [],
                            "Outport": 0,
                            "RConn": [],
                            "Reset": [],
                            "State": [],
                            "Trigger": []
                        },
                        "CompiledPortDataTypes": {
                            "Enable": [],
                            "Ifaction": [],
                            "Inport": [
                                "double",
                                "double"
                            ],
                            "LConn": [],
                            "Outport": [
                                "double"
                            ],
                            "RConn": [],
                            "Reset": [],
                            "State": [],
                            "Trigger": []
                        },
                        "CompiledPortDimensions": {
                            "Enable": [],
                            "Ifaction": [],
                            "Inport": [
                                1,
                                1,
                                1,
                                1
                            ],
                            "LConn": [],
                            "Outport": [
                                1,
                                1
                            ],
                            "RConn": [],
                            "Reset": [],
                            "State": [],
                            "Trigger": []
                        },
                        "CompiledPortWidths": {
                            "Enable": [],
                            "Ifaction": [],
                            "Inport": [
                                1,
                                1
                            ],
                            "LConn": [],
                            "Outport": 1,
                            "RConn": [],
                            "Reset": [],
                            "State": [],
                            "Trigger": []
                        },
                        "CompiledSampleTime": [
                            0.2,
                            0
                        ],
                        "Function": "min",
                        "Handle": 158253.00708007812,
                        "InputSameDT": "off",
                        "Inputs": "2",
                        "LineHandles": {
                            "Enable": [],
                            "Ifaction": [],
                            "Inport": [
                                158260.00732421875,
                                158257.00732421875
                            ],
                            "LConn": [],
                            "Outport": 158259.00732421875,
                            "RConn": [],
                            "Reset": [],
                            "State": [],
                            "Trigger": []
                        },
                        "LockScale": "off",
                        "Name": "upper",
                        "Origin_path": "MultiportSwitch_TestGen13_PP/Satur/upper",
                        "OutDataTypeStr": "Inherit: Inherit via back propagation",
                        "OutMax": "[]",
                        "OutMin": "[]",
                        "Path": "MultiportSwitch_TestGen13_PP/Satur/upper",
                        "PortConnectivity": [
                            {
                                "DstBlock": [],
                                "DstPort": [],
                                "Position": [
                                    105,
                                    95
                                ],
                                "SrcBlock": 158254.00708007812,
                                "SrcPort": 0,
                                "Type": "1"
                            },
                            {
                                "DstBlock": [],
                                "DstPort": [],
                                "Position": [
                                    105,
                                    110
                                ],
                                "SrcBlock": 195.547607421875,
                                "SrcPort": 0,
                                "Type": "2"
                            },
                            {
                                "DstBlock": 196.8116455078125,
                                "DstPort": 0,
                                "Position": [
                                    145,
                                    105
                                ],
                                "SrcBlock": [],
                                "SrcPort": [],
                                "Type": "1"
                            }
                        ],
                        "Ports": [
                            2,
                            1,
                            0,
                            0,
                            0,
                            0,
                            0,
                            0,
                            0
                        ],
                        "Position": [
                            110,
                            87,
                            140,
                            118
                        ],
                        "RndMeth": "Floor",
                        "SampleTime": "-1",
                        "SaturateOnIntegerOverflow": "off",
                        "ZeroCross": "on"
                    },
                    "upper_limit": {
                        "AttributesFormatString": "",
                        "BlockType": "Constant",
                        "CompiledPortComplexSignals": {
                            "Enable": [],
                            "Ifaction": [],
                            "Inport": [],
                            "LConn": [],
                            "Outport": 0,
                            "RConn": [],
                            "Reset": [],
                            "State": [],
                            "Trigger": []
                        },
                        "CompiledPortDataTypes": {
                            "Enable": [],
                            "Ifaction": [],
                            "Inport": [],
                            "LConn": [],
                            "Outport": [
                                "double"
                            ],
                            "RConn": [],
                            "Reset": [],
                            "State": [],
                            "Trigger": []
                        },
                        "CompiledPortDimensions": {
                            "Enable": [],
                            "Ifaction": [],
                            "Inport": [],
                            "LConn": [],
                            "Outport": [
                                1,
                                1
                            ],
                            "RConn": [],
                            "Reset": [],
                            "State": [],
                            "Trigger": []
                        },
                        "CompiledPortWidths": {
                            "Enable": [],
                            "Ifaction": [],
                            "Inport": [],
                            "LConn": [],
                            "Outport": 1,
                            "RConn": [],
                            "Reset": [],
                            "State": [],
                            "Trigger": []
                        },
                        "CompiledSampleTime": [
                            0.2,
                            0
                        ],
                        "FramePeriod": "inf",
                        "Handle": 158254.00708007812,
                        "LineHandles": {
                            "Enable": [],
                            "Ifaction": [],
                            "Inport": [],
                            "LConn": [],
                            "Outport": 158260.00732421875,
                            "RConn": [],
                            "Reset": [],
                            "State": [],
                            "Trigger": []
                        },
                        "LockScale": "off",
                        "Name": "upper_limit",
                        "Origin_path": "MultiportSwitch_TestGen13_PP/Satur/upper_limit",
                        "OutDataTypeStr": "Inherit: Inherit via back propagation",
                        "OutMax": "[]",
                        "OutMin": "[]",
                        "Path": "MultiportSwitch_TestGen13_PP/Satur/upper_limit",
                        "PortConnectivity": {
                            "DstBlock": 158253.00708007812,
                            "DstPort": 0,
                            "Position": [
                                60,
                                65
                            ],
                            "SrcBlock": [],
                            "SrcPort": [],
                            "Type": "1"
                        },
                        "Ports": [
                            0,
                            1,
                            0,
                            0,
                            0,
                            0,
                            0,
                            0,
                            0
                        ],
                        "Position": [
                            25,
                            50,
                            55,
                            80
                        ],
                        "SampleTime": "-1",
                        "Value": "2",
                        "VectorParams1D": "on"
                    }
                },
                "DataTypeOverride": "UseLocalSettings",
                "Handle": 133.8487548828125,
                "IsSubsystemVirtual": "off",
                "LineHandles": {
                    "Enable": [],
                    "Ifaction": [],
                    "Inport": 181.738525390625,
                    "LConn": [],
                    "Outport": 182.593017578125,
                    "RConn": [],
                    "Reset": [],
                    "State": [],
                    "Trigger": []
                },
                "Mask": "off",
                "MaskType": "",
                "MinAlgLoopOccurrences": "off",
                "MinMaxOverflowLogging": "UseLocalSettings",
                "Name": "Satur",
                "Origin_path": "MultiportSwitch_TestGen13_PP/Satur",
                "Path": "MultiportSwitch_TestGen13_PP/Satur",
                "Permissions": "ReadWrite",
                "PermitHierarchicalResolution": "All",
                "PortConnectivity": [
                    {
                        "DstBlock": [],
                        "DstPort": [],
                        "Position": [
                            65,
                            60
                        ],
                        "SrcBlock": 112.957275390625,
                        "SrcPort": 0,
                        "Type": "1"
                    },
                    {
                        "DstBlock": 115.71142578125,
                        "DstPort": 0,
                        "Position": [
                            105,
                            60
                        ],
                        "SrcBlock": [],
                        "SrcPort": [],
                        "Type": "1"
                    }
                ],
                "Ports": [
                    1,
                    1,
                    0,
                    0,
                    0,
                    0,
                    0,
                    0,
                    0
                ],
                "Position": [
                    70,
                    45,
                    100,
                    75
                ],
                "PropExecContextOutsideSubsystem": "off",
                "SFBlockType": "NONE",
                "ShowPortLabels": "FromPortIcon",
                "TemplateBlock": "",
                "TreatAsAtomicUnit": "on",
                "Virtual": "off"
            }
        },
        "Handle": 9.9150390625,
        "Name": "MultiportSwitch_TestGen13_PP",
        "Origin_path": "MultiportSwitch_TestGen13_PP",
        "Path": "MultiportSwitch_TestGen13_PP"
    },
    "meta": {
        "Declarations": {
            "Enumerations": []
        },
        "date": "12-Aug-2021",
        "file_path": "/Users/ktrinh/cocosim/cocosim_github/cocosim_tests/Simulink/unitTests/MultiPortSwitch/MultiportSwitch_TestGen13_PP.slx",
        "sampleTime": 0.2
    }
}
