{
    "Concatenate8_PP": {
        "AllCompiledSampleTimes": [
            [
                0.1,
                0
            ]
        ],
        "BlockType": "block_diagram",
        "CompiledSampleTime": [
            0.1,
            0
        ],
        "Content": {
            "In13": {
                "AttributesFormatString": "",
                "BlockType": "Inport",
                "BusObject": "BusObject",
                "CompiledPortComplexSignals": {
                    "Enable": [],
                    "Ifaction": [],
                    "Inport": [],
                    "LConn": [],
                    "Outport": 0,
                    "RConn": [],
                    "Reset": [],
                    "State": [],
                    "Trigger": []
                },
                "CompiledPortDataTypes": {
                    "Enable": [],
                    "Ifaction": [],
                    "Inport": [],
                    "LConn": [],
                    "Outport": [
                        "double"
                    ],
                    "RConn": [],
                    "Reset": [],
                    "State": [],
                    "Trigger": []
                },
                "CompiledPortDimensions": {
                    "Enable": [],
                    "Ifaction": [],
                    "Inport": [],
                    "LConn": [],
                    "Outport": [
                        2,
                        5,
                        2
                    ],
                    "RConn": [],
                    "Reset": [],
                    "State": [],
                    "Trigger": []
                },
                "CompiledPortWidths": {
                    "Enable": [],
                    "Ifaction": [],
                    "Inport": [],
                    "LConn": [],
                    "Outport": 10,
                    "RConn": [],
                    "Reset": [],
                    "State": [],
                    "Trigger": []
                },
                "CompiledSampleTime": [
                    0.1,
                    0
                ],
                "Handle": 7.2310791015625,
                "LineHandles": {
                    "Enable": [],
                    "Ifaction": [],
                    "Inport": [],
                    "LConn": [],
                    "Outport": 15.6632080078125,
                    "RConn": [],
                    "Reset": [],
                    "State": [],
                    "Trigger": []
                },
                "Name": "In13",
                "Origin_path": "Concatenate8_PP/In13",
                "OutMax": "[]",
                "OutMin": "[]",
                "Path": "Concatenate8_PP/In13",
                "Port": "1",
                "PortConnectivity": {
                    "DstBlock": 10.117431640625,
                    "DstPort": 0,
                    "Position": [
                        360,
                        130
                    ],
                    "SrcBlock": [],
                    "SrcPort": [],
                    "Type": "1"
                },
                "Ports": [
                    0,
                    1,
                    0,
                    0,
                    0,
                    0,
                    0,
                    0,
                    0
                ],
                "Position": [
                    325,
                    123,
                    355,
                    137
                ],
                "UseBusObject": "off"
            },
            "In14": {
                "AttributesFormatString": "",
                "BlockType": "Inport",
                "BusObject": "BusObject",
                "CompiledPortComplexSignals": {
                    "Enable": [],
                    "Ifaction": [],
                    "Inport": [],
                    "LConn": [],
                    "Outport": 0,
                    "RConn": [],
                    "Reset": [],
                    "State": [],
                    "Trigger": []
                },
                "CompiledPortDataTypes": {
                    "Enable": [],
                    "Ifaction": [],
                    "Inport": [],
                    "LConn": [],
                    "Outport": [
                        "double"
                    ],
                    "RConn": [],
                    "Reset": [],
                    "State": [],
                    "Trigger": []
                },
                "CompiledPortDimensions": {
                    "Enable": [],
                    "Ifaction": [],
                    "Inport": [],
                    "LConn": [],
                    "Outport": [
                        1,
                        5
                    ],
                    "RConn": [],
                    "Reset": [],
                    "State": [],
                    "Trigger": []
                },
                "CompiledPortWidths": {
                    "Enable": [],
                    "Ifaction": [],
                    "Inport": [],
                    "LConn": [],
                    "Outport": 5,
                    "RConn": [],
                    "Reset": [],
                    "State": [],
                    "Trigger": []
                },
                "CompiledSampleTime": [
                    0.1,
                    0
                ],
                "Handle": 8.0733642578125,
                "LineHandles": {
                    "Enable": [],
                    "Ifaction": [],
                    "Inport": [],
                    "LConn": [],
                    "Outport": 16.556640625,
                    "RConn": [],
                    "Reset": [],
                    "State": [],
                    "Trigger": []
                },
                "Name": "In14",
                "Origin_path": "Concatenate8_PP/In14",
                "OutMax": "[]",
                "OutMin": "[]",
                "Path": "Concatenate8_PP/In14",
                "Port": "2",
                "PortConnectivity": {
                    "DstBlock": 10.117431640625,
                    "DstPort": 1,
                    "Position": [
                        400,
                        140
                    ],
                    "SrcBlock": [],
                    "SrcPort": [],
                    "Type": "1"
                },
                "Ports": [
                    0,
                    1,
                    0,
                    0,
                    0,
                    0,
                    0,
                    0,
                    0
                ],
                "Position": [
                    365,
                    133,
                    395,
                    147
                ],
                "UseBusObject": "off"
            },
            "In15": {
                "AttributesFormatString": "",
                "BlockType": "Inport",
                "BusObject": "BusObject",
                "CompiledPortComplexSignals": {
                    "Enable": [],
                    "Ifaction": [],
                    "Inport": [],
                    "LConn": [],
                    "Outport": 0,
                    "RConn": [],
                    "Reset": [],
                    "State": [],
                    "Trigger": []
                },
                "CompiledPortDataTypes": {
                    "Enable": [],
                    "Ifaction": [],
                    "Inport": [],
                    "LConn": [],
                    "Outport": [
                        "double"
                    ],
                    "RConn": [],
                    "Reset": [],
                    "State": [],
                    "Trigger": []
                },
                "CompiledPortDimensions": {
                    "Enable": [],
                    "Ifaction": [],
                    "Inport": [],
                    "LConn": [],
                    "Outport": [
                        1,
                        5
                    ],
                    "RConn": [],
                    "Reset": [],
                    "State": [],
                    "Trigger": []
                },
                "CompiledPortWidths": {
                    "Enable": [],
                    "Ifaction": [],
                    "Inport": [],
                    "LConn": [],
                    "Outport": 5,
                    "RConn": [],
                    "Reset": [],
                    "State": [],
                    "Trigger": []
                },
                "CompiledSampleTime": [
                    0.1,
                    0
                ],
                "Handle": 9.0814208984375,
                "LineHandles": {
                    "Enable": [],
                    "Ifaction": [],
                    "Inport": [],
                    "LConn": [],
                    "Outport": 21.782958984375,
                    "RConn": [],
                    "Reset": [],
                    "State": [],
                    "Trigger": []
                },
                "Name": "In15",
                "Origin_path": "Concatenate8_PP/In15",
                "OutMax": "[]",
                "OutMin": "[]",
                "Path": "Concatenate8_PP/In15",
                "Port": "3",
                "PortConnectivity": {
                    "DstBlock": 10.117431640625,
                    "DstPort": 2,
                    "Position": [
                        440,
                        150
                    ],
                    "SrcBlock": [],
                    "SrcPort": [],
                    "Type": "1"
                },
                "Ports": [
                    0,
                    1,
                    0,
                    0,
                    0,
                    0,
                    0,
                    0,
                    0
                ],
                "Position": [
                    405,
                    143,
                    435,
                    157
                ],
                "UseBusObject": "off"
            },
            "Out5": {
                "AttributesFormatString": "",
                "BlockType": "Outport",
                "BusObject": "BusObject",
                "CompiledPortComplexSignals": {
                    "Enable": [],
                    "Ifaction": [],
                    "Inport": 0,
                    "LConn": [],
                    "Outport": [],
                    "RConn": [],
                    "Reset": [],
                    "State": [],
                    "Trigger": []
                },
                "CompiledPortDataTypes": {
                    "Enable": [],
                    "Ifaction": [],
                    "Inport": [
                        "double"
                    ],
                    "LConn": [],
                    "Outport": [],
                    "RConn": [],
                    "Reset": [],
                    "State": [],
                    "Trigger": []
                },
                "CompiledPortDimensions": {
                    "Enable": [],
                    "Ifaction": [],
                    "Inport": [
                        2,
                        5,
                        4
                    ],
                    "LConn": [],
                    "Outport": [],
                    "RConn": [],
                    "Reset": [],
                    "State": [],
                    "Trigger": []
                },
                "CompiledPortWidths": {
                    "Enable": [],
                    "Ifaction": [],
                    "Inport": 20,
                    "LConn": [],
                    "Outport": [],
                    "RConn": [],
                    "Reset": [],
                    "State": [],
                    "Trigger": []
                },
                "CompiledSampleTime": [
                    0.1,
                    0
                ],
                "Handle": 11.132568359375,
                "InitialOutput": "[]",
                "LineHandles": {
                    "Enable": [],
                    "Ifaction": [],
                    "Inport": 12.0909423828125,
                    "LConn": [],
                    "Outport": [],
                    "RConn": [],
                    "Reset": [],
                    "State": [],
                    "Trigger": []
                },
                "Name": "Out5",
                "Origin_path": "Concatenate8_PP/Out5",
                "OutMax": "[]",
                "OutMin": "[]",
                "OutputWhenDisabled": "held",
                "Path": "Concatenate8_PP/Out5",
                "Port": "1",
                "PortConnectivity": {
                    "DstBlock": [],
                    "DstPort": [],
                    "Position": [
                        490,
                        140
                    ],
                    "SrcBlock": 10.117431640625,
                    "SrcPort": 0,
                    "Type": "1"
                },
                "Ports": [
                    1,
                    0,
                    0,
                    0,
                    0,
                    0,
                    0,
                    0,
                    0
                ],
                "Position": [
                    495,
                    133,
                    525,
                    147
                ],
                "UseBusObject": "off"
            },
            "Vector_newline_Concatenate4": {
                "AttributesFormatString": "",
                "BlockType": "Concatenate",
                "CompiledPortComplexSignals": {
                    "Enable": [],
                    "Ifaction": [],
                    "Inport": [
                        0,
                        0,
                        0
                    ],
                    "LConn": [],
                    "Outport": 0,
                    "RConn": [],
                    "Reset": [],
                    "State": [],
                    "Trigger": []
                },
                "CompiledPortDataTypes": {
                    "Enable": [],
                    "Ifaction": [],
                    "Inport": [
                        "double",
                        "double",
                        "double"
                    ],
                    "LConn": [],
                    "Outport": [
                        "double"
                    ],
                    "RConn": [],
                    "Reset": [],
                    "State": [],
                    "Trigger": []
                },
                "CompiledPortDimensions": {
                    "Enable": [],
                    "Ifaction": [],
                    "Inport": [
                        2,
                        5,
                        2,
                        1,
                        5,
                        1,
                        5
                    ],
                    "LConn": [],
                    "Outport": [
                        2,
                        5,
                        4
                    ],
                    "RConn": [],
                    "Reset": [],
                    "State": [],
                    "Trigger": []
                },
                "CompiledPortWidths": {
                    "Enable": [],
                    "Ifaction": [],
                    "Inport": [
                        10,
                        5,
                        5
                    ],
                    "LConn": [],
                    "Outport": 20,
                    "RConn": [],
                    "Reset": [],
                    "State": [],
                    "Trigger": []
                },
                "CompiledSampleTime": [
                    0.1,
                    0
                ],
                "ConcatenateDimension": "2",
                "Handle": 10.117431640625,
                "LineHandles": {
                    "Enable": [],
                    "Ifaction": [],
                    "Inport": [
                        15.6632080078125,
                        16.556640625,
                        21.782958984375
                    ],
                    "LConn": [],
                    "Outport": 12.0909423828125,
                    "RConn": [],
                    "Reset": [],
                    "State": [],
                    "Trigger": []
                },
                "Mode": "Multidimensional array",
                "Name": "Vector_newline_Concatenate4",
                "NumInputs": "3",
                "Origin_path": "Concatenate8_PP/Vector_newline_Concatenate4",
                "Path": "Concatenate8_PP/Vector_newline_Concatenate4",
                "PortConnectivity": [
                    {
                        "DstBlock": [],
                        "DstPort": [],
                        "Position": [
                            445,
                            130
                        ],
                        "SrcBlock": 7.2310791015625,
                        "SrcPort": 0,
                        "Type": "1"
                    },
                    {
                        "DstBlock": [],
                        "DstPort": [],
                        "Position": [
                            445,
                            140
                        ],
                        "SrcBlock": 8.0733642578125,
                        "SrcPort": 0,
                        "Type": "2"
                    },
                    {
                        "DstBlock": [],
                        "DstPort": [],
                        "Position": [
                            445,
                            150
                        ],
                        "SrcBlock": 9.0814208984375,
                        "SrcPort": 0,
                        "Type": "3"
                    },
                    {
                        "DstBlock": 11.132568359375,
                        "DstPort": 0,
                        "Position": [
                            460,
                            140
                        ],
                        "SrcBlock": [],
                        "SrcPort": [],
                        "Type": "1"
                    }
                ],
                "Ports": [
                    3,
                    1,
                    0,
                    0,
                    0,
                    0,
                    0,
                    0,
                    0
                ],
                "Position": [
                    450,
                    121,
                    455,
                    159
                ]
            }
        },
        "Handle": 3.9600830078125,
        "Name": "Concatenate8_PP",
        "Origin_path": "Concatenate8_PP",
        "Path": "Concatenate8_PP"
    },
    "meta": {
        "Declarations": {
            "Enumerations": []
        },
        "date": "01-Nov-2020",
        "file_path": "/Users/ktrinh/cocosim/cocosim_github/cocosim_tests/Simulink/unitTests/Concatenate/Concatenate8_PP.slx",
        "sampleTime": 0.1
    }
}
